feluda/__init__.py
feluda/config.py
feluda/feluda.py
feluda/logger.py
feluda/operator.py
feluda/factory/__init__.py
feluda/factory/audio_factory.py
feluda/factory/image_factory.py
feluda/factory/s3_factory.py
feluda/factory/text_factory.py
feluda/factory/video_factory.py
feluda/operators/__init__.py
feluda-0.10.0.dist-info/METADATA
feluda-0.10.0.dist-info/WHEEL
feluda-0.10.0.dist-info/licenses/LICENSE.md
feluda-0.10.0.dist-info/RECORD
