Metadata-Version: 2.4
Name: feluda
Version: 0.10.0
Summary: A configurable engine for analysing multi-lingual and multi-modal content.
Project-URL: Homepage, https://tattle.co.in/products/feluda/
Project-URL: Repository, https://github.com/tattle-made/feluda
Project-URL: Issues, https://github.com/tattle-made/feluda/issues
Project-URL: Changelog, https://github.com/tattle-made/feluda/blob/main/CHANGELOG.md
Author-email: Tattle Admin <admin@tattle.co.in>
Maintainer-email: Tattle Admin <admin@tattle.co.in>
License:                     GNU GENERAL PUBLIC LICENSE
License-File: LICENSE.md
Keywords: deep-learning,indian-languages,multilingual,multimodal,search
Classifier: Intended Audience :: Developers
Classifier: Intended Audience :: Science/Research
Classifier: License :: OSI Approved :: GNU General Public License v3 (GPLv3)
Classifier: Operating System :: OS Independent
Classifier: Programming Language :: Python :: 3 :: Only
Classifier: Programming Language :: Python :: 3.10
Classifier: Topic :: Multimedia :: Sound/Audio
Classifier: Topic :: Multimedia :: Video
Classifier: Topic :: Scientific/Engineering :: Artificial Intelligence
Classifier: Topic :: Software Development :: Libraries :: Python Modules
Classifier: Topic :: Text Processing :: Linguistic
Requires-Python: >=3.10
Requires-Dist: dacite>=1.9.2
Requires-Dist: pyyaml>=6.0.2
Provides-Extra: all
Requires-Dist: boto3>=1.38.42; extra == 'all'
Requires-Dist: numpy<2.2.0,>=1.26; extra == 'all'
Requires-Dist: pillow>=11.1.0; extra == 'all'
Requires-Dist: pydub>=0.25.1; extra == 'all'
Requires-Dist: requests>=2.32.3; extra == 'all'
Requires-Dist: werkzeug>=3.1.3; extra == 'all'
Requires-Dist: wget>=3.2; extra == 'all'
Provides-Extra: audio
Requires-Dist: boto3>=1.38.42; extra == 'audio'
Requires-Dist: pydub>=0.25.1; extra == 'audio'
Requires-Dist: wget>=3.2; extra == 'audio'
Provides-Extra: dev
Requires-Dist: docformatter>=0.6.0; extra == 'dev'
Requires-Dist: jupyter>=1.1.1; extra == 'dev'
Requires-Dist: memory-profiler>=0.61.0; extra == 'dev'
Requires-Dist: myst-nb>=1.0.0; extra == 'dev'
Requires-Dist: notebook>=7.3.3; extra == 'dev'
Requires-Dist: numpy<2.2.0,>=1.26; extra == 'dev'
Requires-Dist: pre-commit>=4.2.0; extra == 'dev'
Requires-Dist: psutil>=5.9.0; extra == 'dev'
Requires-Dist: pydocstyle>=6.3.0; extra == 'dev'
Requires-Dist: pytest>=8.3.2; extra == 'dev'
Requires-Dist: ruff>=0.11.4; extra == 'dev'
Requires-Dist: sphinx-copybutton>=0.5.0; extra == 'dev'
Requires-Dist: sphinx-design>=0.4.0; extra == 'dev'
Requires-Dist: sphinx-rtd-theme>=1.3.0; extra == 'dev'
Requires-Dist: sphinx>=7.0.0; extra == 'dev'
Requires-Dist: tomlkit>=0.13.2; extra == 'dev'
Provides-Extra: image
Requires-Dist: boto3>=1.38.42; extra == 'image'
Requires-Dist: numpy<2.2.0,>=1.26; extra == 'image'
Requires-Dist: pillow>=11.1.0; extra == 'image'
Requires-Dist: requests>=2.32.3; extra == 'image'
Requires-Dist: werkzeug>=3.1.3; extra == 'image'
Requires-Dist: wget>=3.2; extra == 'image'
Provides-Extra: video
Requires-Dist: boto3>=1.38.42; extra == 'video'
Requires-Dist: werkzeug>=3.1.3; extra == 'video'
Requires-Dist: wget>=3.2; extra == 'video'
